pyromenu/__init__.py
pyromenu/fakes.py
pyromenu/kbutton.py
pyromenu/kmenu.py
pyromenu/krow.py
pyromenu/abc/__init__.py
pyromenu/abc/button.py
pyromenu/abc/menu.py
pyromenu/abc/row.py
pyromenu-2.0.dist-info/LICENSE
pyromenu-2.0.dist-info/METADATA
pyromenu-2.0.dist-info/WHEEL
pyromenu-2.0.dist-info/top_level.txt
pyromenu-2.0.dist-info/RECORD
