Metadata-Version: 2.1
Name: pyromenu
Version: 2.0
Summary: Object-oriented way to build telegram keyboard-menus
Home-page: https://github.com/IlhomBahoraliev/pyromenu
Author: LidaRandom
Author-email: bahoralievdev@yandex.com
License: UNKNOWN
Platform: UNKNOWN
Classifier: Programming Language :: Python :: 3
Classifier: License :: OSI Approved :: MIT License
Classifier: Operating System :: OS Independent
Requires-Python: >=3.6
Requires-Dist: pyaes (==1.6.1)
Requires-Dist: Pyrogram (==0.16.0)
Requires-Dist: PySocks (==1.7.0)
